SmilesPE/__init__.py
SmilesPE/_nbdev.py
SmilesPE/learner.py
SmilesPE/pretokenizer.py
SmilesPE/spe2vec.py
SmilesPE/tokenizer.py
SmilesPE-0.0.3.dist-info/LICENSE
SmilesPE-0.0.3.dist-info/METADATA
SmilesPE-0.0.3.dist-info/WHEEL
SmilesPE-0.0.3.dist-info/entry_points.txt
SmilesPE-0.0.3.dist-info/top_level.txt
SmilesPE-0.0.3.dist-info/RECORD
