Metadata-Version: 2.1
Name: SmilesPE
Version: 0.0.3
Summary: Tokenize SMILES with substructure units
Home-page: https://github.com/XinhaoLi74/SmilesPE
Author: Xinhao Li
Author-email: xli74@ncsu.edu
License: Apache Software License 2.0
Keywords: Cheminformatics SMILES
Platform: UNKNOWN
Classifier: Development Status :: 3 - Alpha
Classifier: Intended Audience :: Developers
Classifier: License :: OSI Approved :: Apache Software License
Classifier: Natural Language :: English
Classifier: Programming Language :: Python :: 3.6
Classifier: Programming Language :: Python :: 3.7
Classifier: Programming Language :: Python :: 3.8
Requires-Python: >=3.6
Requires-Dist: fastprogress
Requires-Dist: gensim
